aiogrouper
