Metadata-Version: 1.0
Name: aiogrouper
Version: 0.1.5
Summary: Client library for Internet2's Grouper, using asyncio.
Home-page: UNKNOWN
Author: University of Oxford
Author-email: github@it.ox.ac.uk
License: BSD
Platform: UNKNOWN
